signethic/__init__.py
signethic-0.3.1.dist-info/LICENSE.txt
signethic-0.3.1.dist-info/METADATA
signethic-0.3.1.dist-info/WHEEL
signethic-0.3.1.dist-info/entry_points.txt
signethic-0.3.1.dist-info/top_level.txt
signethic-0.3.1.dist-info/RECORD
