Metadata-Version: 2.1
Name: signethic
Version: 0.3.1
Summary: Object signing and signature verification module
Home-page: http://github.com/dionresearch/signethic
Author: Francois Dion
Author-email: fdion@dionresearch.com
License: MIT
Platform: UNKNOWN
Classifier: Programming Language :: Python :: 3
Classifier: License :: OSI Approved :: MIT License
Classifier: Operating System :: OS Independent
License-File: LICENSE.txt
Requires-Dist: pycryptodome
